{
    "asreviewVersion": "1.5",
    "apiVersion": "1.1.2",
    "data": {
        "items": [
            {
                "id": "recall",
                "title": "Recall",
                "value": [
                    [
                        0.1,
                        0.6746031746031746
                    ],
                    [
                        0.25,
                        0.6904761904761905
                    ],
                    [
                        0.5,
                        0.9920634920634921
                    ],
                    [
                        0.75,
                        1.0
                    ],
                    [
                        0.9,
                        1.0
                    ]
                ]
            },
            {
                "id": "wss",
                "title": "Work Saved over Sampling",
                "value": [
                    [
                        0.95,
                        0.6195177520410101
                    ]
                ]
            },
            {
                "id": "erf",
                "title": "Extra Relevant record Found",
                "value": [
                    [
                        0.1,
                        0.5714285714285714
                    ]
                ]
            },
            {
                "id": "atd",
                "title": "Average time to discovery",
                "value": 649.3095238095239
            },
            {
                "id": "td",
                "title": "Time to discovery",
                "value": [
                    [
                        5044,
                        14
                    ],
                    [
                        4644,
                        20
                    ],
                    [
                        5210,
                        22
                    ],
                    [
                        5000,
                        26
                    ],
                    [
                        4878,
                        27
                    ],
                    [
                        4625,
                        28
                    ],
                    [
                        4739,
                        29
                    ],
                    [
                        4650,
                        30
                    ],
                    [
                        4676,
                        32
                    ],
                    [
                        4990,
                        35
                    ],
                    [
                        4947,
                        38
                    ],
                    [
                        5258,
                        46
                    ],
                    [
                        4876,
                        48
                    ],
                    [
                        5066,
                        50
                    ],
                    [
                        5041,
                        51
                    ],
                    [
                        4966,
                        54
                    ],
                    [
                        4647,
                        59
                    ],
                    [
                        4725,
                        60
                    ],
                    [
                        4710,
                        61
                    ],
                    [
                        5062,
                        62
                    ],
                    [
                        5048,
                        63
                    ],
                    [
                        5086,
                        65
                    ],
                    [
                        4836,
                        66
                    ],
                    [
                        4906,
                        68
                    ],
                    [
                        5197,
                        69
                    ],
                    [
                        4697,
                        73
                    ],
                    [
                        5166,
                        74
                    ],
                    [
                        4793,
                        81
                    ],
                    [
                        4982,
                        83
                    ],
                    [
                        4740,
                        87
                    ],
                    [
                        4577,
                        92
                    ],
                    [
                        4655,
                        93
                    ],
                    [
                        4844,
                        95
                    ],
                    [
                        4580,
                        96
                    ],
                    [
                        5109,
                        97
                    ],
                    [
                        4686,
                        99
                    ],
                    [
                        4656,
                        100
                    ],
                    [
                        4736,
                        102
                    ],
                    [
                        4654,
                        106
                    ],
                    [
                        4788,
                        107
                    ],
                    [
                        5262,
                        108
                    ],
                    [
                        4988,
                        109
                    ],
                    [
                        4800,
                        114
                    ],
                    [
                        4585,
                        119
                    ],
                    [
                        5161,
                        129
                    ],
                    [
                        4985,
                        136
                    ],
                    [
                        4653,
                        143
                    ],
                    [
                        4548,
                        146
                    ],
                    [
                        5021,
                        148
                    ],
                    [
                        4834,
                        150
                    ],
                    [
                        4609,
                        158
                    ],
                    [
                        4857,
                        160
                    ],
                    [
                        4806,
                        164
                    ],
                    [
                        4750,
                        165
                    ],
                    [
                        5002,
                        166
                    ],
                    [
                        4743,
                        167
                    ],
                    [
                        4688,
                        169
                    ],
                    [
                        4954,
                        178
                    ],
                    [
                        4923,
                        195
                    ],
                    [
                        4597,
                        198
                    ],
                    [
                        4621,
                        201
                    ],
                    [
                        4936,
                        207
                    ],
                    [
                        4903,
                        209
                    ],
                    [
                        4883,
                        213
                    ],
                    [
                        5113,
                        222
                    ],
                    [
                        4984,
                        228
                    ],
                    [
                        4672,
                        230
                    ],
                    [
                        4837,
                        236
                    ],
                    [
                        4852,
                        247
                    ],
                    [
                        5118,
                        258
                    ],
                    [
                        4879,
                        266
                    ],
                    [
                        4801,
                        272
                    ],
                    [
                        4991,
                        275
                    ],
                    [
                        5181,
                        329
                    ],
                    [
                        5036,
                        331
                    ],
                    [
                        4551,
                        345
                    ],
                    [
                        4568,
                        352
                    ],
                    [
                        4973,
                        361
                    ],
                    [
                        4962,
                        364
                    ],
                    [
                        5219,
                        372
                    ],
                    [
                        5152,
                        390
                    ],
                    [
                        5223,
                        400
                    ],
                    [
                        4669,
                        423
                    ],
                    [
                        5104,
                        428
                    ],
                    [
                        4861,
                        511
                    ],
                    [
                        4981,
                        589
                    ],
                    [
                        5160,
                        860
                    ],
                    [
                        767,
                        1474
                    ],
                    [
                        2545,
                        1604
                    ],
                    [
                        1881,
                        1605
                    ],
                    [
                        902,
                        1614
                    ],
                    [
                        4461,
                        1615
                    ],
                    [
                        1746,
                        1616
                    ],
                    [
                        3680,
                        1620
                    ],
                    [
                        3769,
                        1624
                    ],
                    [
                        1429,
                        1634
                    ],
                    [
                        462,
                        1636
                    ],
                    [
                        2624,
                        1640
                    ],
                    [
                        51,
                        1642
                    ],
                    [
                        1180,
                        1644
                    ],
                    [
                        4269,
                        1648
                    ],
                    [
                        3608,
                        1650
                    ],
                    [
                        1033,
                        1651
                    ],
                    [
                        2279,
                        1654
                    ],
                    [
                        2740,
                        1657
                    ],
                    [
                        4201,
                        1660
                    ],
                    [
                        116,
                        1669
                    ],
                    [
                        4327,
                        1670
                    ],
                    [
                        1356,
                        1672
                    ],
                    [
                        3076,
                        1674
                    ],
                    [
                        2496,
                        1675
                    ],
                    [
                        1994,
                        1676
                    ],
                    [
                        4154,
                        1678
                    ],
                    [
                        831,
                        1680
                    ],
                    [
                        953,
                        1681
                    ],
                    [
                        3842,
                        1683
                    ],
                    [
                        4377,
                        1688
                    ],
                    [
                        1554,
                        1690
                    ],
                    [
                        1514,
                        1691
                    ],
                    [
                        3314,
                        1701
                    ],
                    [
                        1248,
                        1702
                    ],
                    [
                        2803,
                        1707
                    ],
                    [
                        730,
                        1709
                    ],
                    [
                        1565,
                        1778
                    ],
                    [
                        3442,
                        1934
                    ],
                    [
                        4565,
                        3918
                    ]
                ]
            }
        ]
    }
}